x12306/__init__.py
x12306/__version__.py
x12306/exceptions.py
x12306/settings.py
x12306/train.py
x12306/utils.py
x12306/data/cdn.txt
x12306/data/proxies.txt
x12306/data/stations.2019.txt
x12306/data/stations.txt
x12306-0.3.2.dist-info/LICENSE
x12306-0.3.2.dist-info/METADATA
x12306-0.3.2.dist-info/WHEEL
x12306-0.3.2.dist-info/entry_points.txt
x12306-0.3.2.dist-info/top_level.txt
x12306-0.3.2.dist-info/RECORD
